{
  "124977557560410": {
    "jobs": {
      "0ac01a37-e676-b074-3f71-e9f05ad3d587": {
        "placeVersion": 44,
        "lastUpdated": "2025-09-29T15:22:13.931Z"
      }
    },
    "lastUpdated": "2025-09-29T15:22:13.931Z",
    "createdAt": "2025-09-29T15:22:13.931Z"
  },
  "126884695634066": {
    "jobs": {
      "bce570b4-15bd-4cff-ad6f-5a1101627fcb": {
        "placeVersion": 1921,
        "lastUpdated": "2025-09-29T15:25:04.980Z"
      }
    },
    "lastUpdated": "2025-09-29T15:25:04.980Z",
    "createdAt": "2025-09-29T15:25:04.980Z"
  }
}